anzechanel/__init__.py
anzechanel/audio/__init__.py
anzechanel/video/__init__.py
test/__init__.py
anzechannel-2023.9.1.dist-info/LICENSE.txt
anzechannel-2023.9.1.dist-info/METADATA
anzechannel-2023.9.1.dist-info/WHEEL
anzechannel-2023.9.1.dist-info/top_level.txt
anzechannel-2023.9.1.dist-info/RECORD
