Metadata-Version: 2.1
Name: anzechannel
Version: 2023.9.1
Summary: 这是一个关于安泽频道的软件包。
Author: anzechannel
Author-email: 348834851@qq.com
Classifier: Programming Language :: Python :: 3
Classifier: License :: OSI Approved :: MIT License
Classifier: Operating System :: OS Independent
Requires-Python: >=3.8
License-File: LICENSE.txt
